nordpool/__init__.py
nordpool/elspot.py
nordpool-0.5.1.dist-info/METADATA
nordpool-0.5.1.dist-info/WHEEL
nordpool-0.5.1.dist-info/licenses/LICENSE
nordpool-0.5.1.dist-info/RECORD
