Metadata-Version: 2.4
Name: nordpool
Version: 0.5.1
Summary: Python library for fetching Nord Pool spot prices.
License: MIT
License-File: LICENSE
Author: Kimmo Huoman
Author-email: kipenroskaposti@gmail.com
Requires-Python: >=3.9,<4.0
Classifier: License :: OSI Approved :: MIT License
Classifier: Programming Language :: Python :: 3
Classifier: Programming Language :: Python :: 3.9
Classifier: Programming Language :: Python :: 3.10
Classifier: Programming Language :: Python :: 3.11
Classifier: Programming Language :: Python :: 3.12
Classifier: Programming Language :: Python :: 3.13
Classifier: Programming Language :: Python :: 3.14
Requires-Dist: python-dateutil (>=2.9.0.post0,<3.0.0)
Requires-Dist: pytz (>=2024.2)
Requires-Dist: requests (>=2.32.3,<3.0.0)
Project-URL: Homepage, https://github.com/kipe/nordpool
Project-URL: Repository, https://github.com/kipe/nordpool
